[
  {
    "package_id": 3,
    "package_name": "Standard",
    "monthly_cost": 39.0,
    "annual_cost": 599.0,
    "percentage": 12.6
  },
  {
    "package_id": 1,
    "package_name": "Starter",
    "monthly_cost": 99.0,
    "annual_cost": 599.0,
    "percentage": 11.6
  },
  {
    "package_id": 10,
    "package_name": "VIP",
    "monthly_cost": 49.0,
    "annual_cost": 599.0,
    "percentage": 10.4
  },
  {
    "package_id": 2,
    "package_name": "Basic",
    "monthly_cost": 19.0,
    "annual_cost": 299.0,
    "percentage": 10.4
  }
]